{
  "1891": "{\"mg:__init__\":{\"0\":0.3373258896},\"mg:_setup_relaxation\":{\"0\":0.1444541924},\"mg:_setup_hierarchy\":{\"0\":0.0857205242},\"mg:_get_amg_interp\":{\"0\":0.0762812905},\"lsc:__init__\":{\"0\":0.0025244839}}",
  "7235": "{\"mg:__init__\":{\"0\":0.4028766975},\"mg:_setup_relaxation\":{\"0\":0.1460062228},\"mg:_setup_hierarchy\":{\"0\":0.1277724318},\"mg:_get_amg_interp\":{\"0\":0.1104960367},\"lsc:__init__\":{\"0\":0.0058273971}}",
  "28291": "{\"mg:__init__\":{\"0\":0.7182788812,\"1\":null},\"mg:_setup_hierarchy\":{\"0\":0.3682692274,\"1\":null},\"mg:_get_amg_interp\":{\"0\":0.3001600057,\"1\":null},\"mg:_setup_relaxation\":{\"0\":0.2407674603,\"1\":null},\"lsc:__init__\":{\"0\":0.0209202319,\"1\":0.0210236944}}",
  "111875": "{\"mg:__init__\":{\"0\":2.0635800734,\"1\":null},\"mg:_setup_hierarchy\":{\"0\":1.3095061332,\"1\":null},\"mg:_get_amg_interp\":{\"0\":1.0610130429,\"1\":null},\"mg:_setup_relaxation\":{\"0\":0.4457321018,\"1\":null},\"lsc:__init__\":{\"0\":0.0802917592,\"1\":0.0808354914}}",
  "444931": "{\"mg:__init__\":{\"0\":6.6080768704,\"1\":null,\"2\":null},\"mg:_setup_hierarchy\":{\"0\":5.2500483207,\"1\":null,\"2\":null},\"mg:_get_amg_interp\":{\"0\":4.2348587699,\"1\":null,\"2\":null},\"mg:_setup_relaxation\":{\"0\":1.2185470685,\"1\":null,\"2\":null},\"lsc:__init__\":{\"0\":0.3362420872,\"1\":0.3008906133,\"2\":0.072177548}}",
  "1774595": "{\"mg:__init__\":{\"0\":29.9199901484,\"1\":null,\"2\":null},\"mg:_setup_hierarchy\":{\"0\":24.682186801,\"1\":null,\"2\":null},\"mg:_get_amg_interp\":{\"0\":20.3352240138,\"1\":null,\"2\":null},\"mg:_setup_relaxation\":{\"0\":4.2778476067,\"1\":null,\"2\":null},\"lsc:__init__\":{\"0\":1.4631644636,\"1\":1.2566603087,\"2\":0.3067453615}}",
  "3314503": "{\"mg:__init__\":{\"0\":55.1187655143,\"1\":null,\"2\":null,\"3\":null},\"mg:_setup_hierarchy\":{\"0\":46.973668687,\"1\":null,\"2\":null,\"3\":null},\"mg:_get_amg_interp\":{\"0\":38.5166136585,\"1\":null,\"2\":null,\"3\":null},\"mg:_setup_relaxation\":{\"0\":8.0242154859,\"1\":null,\"2\":null,\"3\":null},\"lsc:__init__\":{\"0\":3.045035582,\"1\":2.3262244985,\"2\":0.5389325395,\"3\":0.1058675125}}",
  "4328003": "{\"mg:__init__\":{\"0\":74.2743858136,\"1\":null,\"2\":null,\"3\":null},\"mg:_setup_hierarchy\":{\"0\":63.7461970262,\"1\":null,\"2\":null,\"3\":null},\"mg:_get_amg_interp\":{\"0\":52.3182259351,\"1\":null,\"2\":null,\"3\":null},\"mg:_setup_relaxation\":{\"0\":10.3944476619,\"1\":null,\"2\":null,\"3\":null},\"lsc:__init__\":{\"0\":3.9532454051,\"1\":3.0390282348,\"2\":0.767949149,\"3\":0.1317830943}}"
}