{
  "15440602": "{\"dofs\":{\"0\":8825602,\"1\":1538616,\"2\":362370,\"3\":27116,\"4\":2568,\"5\":262,\"6\":30},\"nnz\":{\"0\":101129146,\"1\":93859216,\"2\":56866970,\"3\":3625952,\"4\":319220,\"5\":20274,\"6\":450},\"nnz(%)\":{\"0\":39.53,\"1\":36.69,\"2\":22.23,\"3\":1.42,\"4\":0.12,\"5\":0.01,\"6\":0.0},\"CR\":{\"0\":5.74,\"1\":4.25,\"2\":13.36,\"3\":10.56,\"4\":9.8,\"5\":8.73,\"6\":null},\"Ratio[v\\/p]\":{\"0\":0.0,\"1\":0.0,\"2\":0.0,\"3\":0.0,\"4\":0.0,\"5\":0.0,\"6\":0.0},\"CR(u)\":{\"0\":5.736,\"1\":4.246,\"2\":13.364,\"3\":10.559,\"4\":9.802,\"5\":8.733,\"6\":null},\"dofs(u)\":{\"0\":8825602,\"1\":1538616,\"2\":362370,\"3\":27116,\"4\":2568,\"5\":262,\"6\":30},\"O(ml)\":{\"0\":2.53,\"1\":null,\"2\":null,\"3\":null,\"4\":null,\"5\":null,\"6\":null},\"O(ml(A))\":{\"0\":1.219,\"1\":null,\"2\":null,\"3\":null,\"4\":null,\"5\":null,\"6\":null},\"O(u)\":{\"0\":2.5296488512,\"1\":null,\"2\":null,\"3\":null,\"4\":null,\"5\":null,\"6\":null}}",
  "8261634": "{\"dofs\":{\"0\":4722690,\"1\":823964,\"2\":193092,\"3\":14436,\"4\":1398,\"5\":140},\"nnz\":{\"0\":54072824,\"1\":50173340,\"2\":30017724,\"3\":1877456,\"4\":162046,\"5\":8068},\"nnz(%)\":{\"0\":39.67,\"1\":36.81,\"2\":22.02,\"3\":1.38,\"4\":0.12,\"5\":0.01},\"CR\":{\"0\":5.73,\"1\":4.27,\"2\":13.38,\"3\":10.33,\"4\":9.99,\"5\":null},\"Ratio[v\\/p]\":{\"0\":0.0,\"1\":0.0,\"2\":0.0,\"3\":0.0,\"4\":0.0,\"5\":0.0},\"CR(u)\":{\"0\":5.732,\"1\":4.267,\"2\":13.376,\"3\":10.326,\"4\":9.986,\"5\":null},\"dofs(u)\":{\"0\":4722690,\"1\":823964,\"2\":193092,\"3\":14436,\"4\":1398,\"5\":140},\"O(ml)\":{\"0\":2.521,\"1\":null,\"2\":null,\"3\":null,\"4\":null,\"5\":null},\"O(ml(A))\":{\"0\":1.219,\"1\":null,\"2\":null,\"3\":null,\"4\":null,\"5\":null},\"O(u)\":{\"0\":2.5208866102,\"1\":null,\"2\":null,\"3\":null,\"4\":null,\"5\":null}}",
  "2066434": "{\"dofs\":{\"0\":1181698,\"1\":206360,\"2\":47358,\"3\":3642,\"4\":350,\"5\":44},\"nnz\":{\"0\":13488166,\"1\":12470828,\"2\":7091366,\"3\":437894,\"4\":29282,\"5\":968},\"nnz(%)\":{\"0\":40.24,\"1\":37.21,\"2\":21.16,\"3\":1.31,\"4\":0.09,\"5\":0.0},\"CR\":{\"0\":5.73,\"1\":4.36,\"2\":13.0,\"3\":10.41,\"4\":7.95,\"5\":null},\"Ratio[v\\/p]\":{\"0\":0.0,\"1\":0.0,\"2\":0.0,\"3\":0.0,\"4\":0.0,\"5\":0.0},\"CR(u)\":{\"0\":5.726,\"1\":4.357,\"2\":13.003,\"3\":10.406,\"4\":7.955,\"5\":null},\"dofs(u)\":{\"0\":1181698,\"1\":206360,\"2\":47358,\"3\":3642,\"4\":350,\"5\":44},\"O(ml)\":{\"0\":2.485,\"1\":null,\"2\":null,\"3\":null,\"4\":null,\"5\":null},\"O(ml(A))\":{\"0\":1.218,\"1\":null,\"2\":null,\"3\":null,\"4\":null,\"5\":null},\"O(u)\":{\"0\":2.4850305075,\"1\":null,\"2\":null,\"3\":null,\"4\":null,\"5\":null}}",
  "517122": "{\"dofs\":{\"0\":295938,\"1\":51670,\"2\":11338,\"3\":904,\"4\":100},\"nnz\":{\"0\":3357650,\"1\":3072266,\"2\":1563666,\"3\":89544,\"4\":4648},\"nnz(%)\":{\"0\":41.52,\"1\":37.99,\"2\":19.33,\"3\":1.11,\"4\":0.06},\"CR\":{\"0\":5.73,\"1\":4.56,\"2\":12.54,\"3\":9.04,\"4\":null},\"Ratio[v\\/p]\":{\"0\":0.0,\"1\":0.0,\"2\":0.0,\"3\":0.0,\"4\":0.0},\"CR(u)\":{\"0\":5.727,\"1\":4.557,\"2\":12.542,\"3\":9.04,\"4\":null},\"dofs(u)\":{\"0\":295938,\"1\":51670,\"2\":11338,\"3\":904,\"4\":100},\"O(ml)\":{\"0\":2.409,\"1\":null,\"2\":null,\"3\":null,\"4\":null},\"O(ml(A))\":{\"0\":1.216,\"1\":null,\"2\":null,\"3\":null,\"4\":null},\"O(u)\":{\"0\":2.4087602937,\"1\":null,\"2\":null,\"3\":null,\"4\":null}}",
  "129538": "{\"dofs\":{\"0\":74242,\"1\":12986,\"2\":2684,\"3\":232},\"nnz\":{\"0\":832222,\"1\":748106,\"2\":319400,\"3\":15764},\"nnz(%)\":{\"0\":43.45,\"1\":39.06,\"2\":16.67,\"3\":0.82},\"CR\":{\"0\":5.72,\"1\":4.84,\"2\":11.57,\"3\":null},\"Ratio[v\\/p]\":{\"0\":0.0,\"1\":0.0,\"2\":0.0,\"3\":0.0},\"CR(u)\":{\"0\":5.717,\"1\":4.838,\"2\":11.569,\"3\":null},\"dofs(u)\":{\"0\":74242,\"1\":12986,\"2\":2684,\"3\":232},\"O(ml)\":{\"0\":2.302,\"1\":null,\"2\":null,\"3\":null},\"O(ml(A))\":{\"0\":1.214,\"1\":null,\"2\":null,\"3\":null},\"O(u)\":{\"0\":2.3016598936,\"1\":null,\"2\":null,\"3\":null}}",
  "32514": "{\"dofs\":{\"0\":18690,\"1\":3266,\"2\":624,\"3\":64},\"nnz\":{\"0\":204406,\"1\":175958,\"2\":55112,\"3\":2040},\"nnz(%)\":{\"0\":46.72,\"1\":40.22,\"2\":12.6,\"3\":0.47},\"CR\":{\"0\":5.72,\"1\":5.23,\"2\":9.75,\"3\":null},\"Ratio[v\\/p]\":{\"0\":0.0,\"1\":0.0,\"2\":0.0,\"3\":0.0},\"CR(u)\":{\"0\":5.723,\"1\":5.234,\"2\":9.75,\"3\":null},\"dofs(u)\":{\"0\":18690,\"1\":3266,\"2\":624,\"3\":64},\"O(ml)\":{\"0\":2.14,\"1\":null,\"2\":null,\"3\":null},\"O(ml(A))\":{\"0\":1.212,\"1\":null,\"2\":null,\"3\":null},\"O(u)\":{\"0\":2.1404264063,\"1\":null,\"2\":null,\"3\":null}}",
  "8194": "{\"dofs\":{\"0\":4738,\"1\":824,\"2\":146},\"nnz\":{\"0\":49284,\"1\":38480,\"2\":7382},\"nnz(%)\":{\"0\":51.8,\"1\":40.44,\"2\":7.76},\"CR\":{\"0\":5.75,\"1\":5.64,\"2\":null},\"Ratio[v\\/p]\":{\"0\":0.0,\"1\":0.0,\"2\":0.0},\"CR(u)\":{\"0\":5.75,\"1\":5.644,\"2\":null},\"dofs(u)\":{\"0\":4738,\"1\":824,\"2\":146},\"O(ml)\":{\"0\":1.931,\"1\":null,\"2\":null},\"O(ml(A))\":{\"0\":1.205,\"1\":null,\"2\":null},\"O(u)\":{\"0\":1.9305657008,\"1\":null,\"2\":null}}"
}